{"abstracts-retrieval-response": {"item": {"ait:process-info": {"ait:status": {"@state": "update", "@type": "core", "@stage": "S300"}, "ait:date-delivered": {"@day": "10", "@timestamp": "2021-10-10T01:28:01.000001-04:00", "@year": "2021", "@month": "10"}, "ait:date-sort": {"@day": "02", "@year": "2015", "@month": "11"}}, "bibrecord": {"head": {"author-group": {"affiliation": {"country": "Thailand", "address-part": "Rama 1 Road, Phatumwan", "postal-code": "10330", "@afid": "60028190", "@country": "tha", "city": "Bangkok", "organization": {"$": "Chulalongkorn University"}, "affiliation-id": {"@afid": "60028190"}}, "author": [{"ce:given-name": "Somruthai", "preferred-name": {"ce:given-name": "Somruthai", "ce:initials": "S.", "ce:surname": "Soontayatron", "ce:indexed-name": "Soontayatron S."}, "@seq": "1", "ce:initials": "S.", "@_fa": "true", "@type": "auth", "ce:surname": "Soontayatron", "@auid": "55875068200", "ce:indexed-name": "Soontayatron S."}]}, "citation-title": "Residents\u2019 Perceptions Towards Sociocultural Impacts Induced by Internal Migration", "abstracts": "\u00a9 2014 Asia Pacific Tourism Association.The economic development brought about by tourism often induces migration to an emerging tourism region. A constructivist paradigm with semi-structured interviews was employed. This paper aims to interpret residents' social constructions towards the sociocultural impacts of tourism-induced internal labour migration in a Thai context. Western studies assume there are clear negative and positive impacts of tourism development. These sociocultural impacts of tourism in the Western literature are applicable in a Thai context. However, most previous studies on sociocultural impacts of tourism look from the outside but it is significant that nobody has looked from an inside Thai perspective. Local residents in Koh Samui attribute the majority of sociocultural impacts to labour migration from the Isan region of Thailand. This paper starts with an analysis of labour forces in Thailand, and how tourism and labour migration are interrelated. In addition, the ethnic identity of the Isan people is examined.", "correspondence": {"affiliation": {"country": "Thailand", "address-part": "Rama 1 Road, Phatumwan", "postal-code": "10330", "@country": "tha", "city": "Bangkok", "organization": {"$": "Chulalongkorn University"}}, "person": {"ce:given-name": "Somruthai", "ce:initials": "S.", "ce:surname": "Soontayatron", "ce:indexed-name": "Soontayatron S."}}, "citation-info": {"author-keywords": {"author-keyword": [{"$": "internal migration", "@xml:lang": "eng"}, {"$": "Isan migrant workers", "@xml:lang": "eng"}, {"$": "residents\u2019 perceptions", "@xml:lang": "eng"}, {"$": "sociocultural impacts", "@xml:lang": "eng"}, {"$": "tourism development", "@xml:lang": "eng"}]}, "citation-type": {"@code": "ar"}, "citation-language": {"@language": "English", "@xml:lang": "eng"}, "abstract-language": {"@language": "English", "@xml:lang": "eng"}}, "source": {"sourcetitle-abbrev": "Asia Pac. J. Tour. Res.", "website": {"ce:e-address": {"$": "http://www.tandf.co.uk/journals/titles/10941665.asp", "@type": "email"}}, "@country": "gbr", "translated-sourcetitle": {"$": "Asia Pacific Journal of Tourism Research", "@xml:lang": "eng"}, "issn": [{"$": "17416507", "@type": "electronic"}, {"$": "10941665", "@type": "print"}], "volisspag": {"voliss": {"@volume": "20", "@issue": "11"}, "pagerange": {"@first": "1234", "@last": "1245"}}, "@type": "j", "publicationyear": {"@first": "2015"}, "publisher": {"publishername": "Routledge"}, "sourcetitle": "Asia Pacific Journal of Tourism Research", "@srcid": "12117", "publicationdate": {"month": "11", "year": "2015", "date-text": {"@xfab-added": "true", "$": "2 November 2015"}, "day": "02"}}, "enhancement": {"classificationgroup": {"classifications": [{"@type": "GEOCLASS", "classification": [{"classification-code": "70.6.4", "classification-description": "Migration"}, {"classification-code": "74.18", "classification-description": "MIGRATION, REFUGEES, RESETTLEMENT. LABOUR MIGRATION"}]}, {"@type": "ASJC", "classification": [{"$": "3305"}, {"$": "1409"}]}, {"@type": "SUBJABBR", "classification": [{"$": "SOCI"}, {"$": "BUSI"}]}]}}}, "item-info": {"copyright": {"$": "Copyright 2021 Elsevier B.V., All rights reserved.", "@type": "Elsevier"}, "dbcollection": [{"$": "GEO"}, {"$": "REAXYSCAR"}, {"$": "SCOPUS"}, {"$": "Scopusbase"}], "history": {"date-created": {"@day": "27", "@timestamp": "BST 09:12:13", "@year": "2021", "@month": "09"}}, "itemidlist": {"itemid": [{"$": "600555842", "@idtype": "PUI"}, {"$": "630148459", "@idtype": "CAR-ID"}, {"$": "4537254", "@idtype": "GEO"}, {"$": "20213799726", "@idtype": "REAXYSCAR"}, {"$": "20143620593", "@idtype": "SCOPUS"}, {"$": "84943448265", "@idtype": "SCP"}, {"$": "84943448265", "@idtype": "SGR"}], "ce:doi": "10.1080/10941665.2014.975826"}}, "tail": {"bibliography": {"@refcount": "57", "reference": [{"ref-fulltext": "L.R.Allen,, H.Hafer,, P.Long,, & R.Perdue, (1993). Rural residents\u2019 attitudes towards recreation and tourism development. Journal of Travel Research, 31(4), 27\u201333. doi: 10.1177/004728759303100405", "@id": "1", "ref-info": {"ref-publicationyear": {"@first": "1993"}, "ref-title": {"ref-titletext": "Rural residents\u2019 attitudes towards recreation and tourism development"}, "refd-itemidlist": {"itemid": {"$": "0027505443", "@idtype": "SGR"}}, "ref-volisspag": {"voliss": {"@volume": "31", "@issue": "4"}, "pagerange": {"@first": "27", "@last": "33"}}, "ref-authors": {"author": [{"@seq": "1", "ce:initials": "L.R.", "@_fa": "true", "ce:surname": "Allen", "ce:indexed-name": "Allen L.R."}, {"@seq": "2", "ce:initials": "H.", "@_fa": "true", "ce:surname": "Hafer", "ce:indexed-name": "Hafer H."}, {"@seq": "3", "ce:initials": "P.", "@_fa": "true", "ce:surname": "Long", "ce:indexed-name": "Long P."}, {"@seq": "4", "ce:initials": "R.", "@_fa": "true", "ce:surname": "Perdue", "ce:indexed-name": "Perdue R."}]}, "ref-sourcetitle": "Journal of Travel Research"}}, {"ref-fulltext": "K.L.Andereck,, K.M.Valentine,, R.C.Knopf,, & C.A.Vogt, (2005). Residents\u2019 perceptions of community tourism impacts. Annals of Tourism Research, 32(4), 1056\u20131076. doi: 10.1016/j.annals.2005.03.001", "@id": "2", "ref-info": {"ref-publicationyear": {"@first": "2005"}, "ref-title": {"ref-titletext": "Residents\u2019 perceptions of community tourism impacts"}, "refd-itemidlist": {"itemid": {"$": "27744581644", "@idtype": "SGR"}}, "ref-volisspag": {"voliss": {"@volume": "32", "@issue": "4"}, "pagerange": {"@first": "1056", "@last": "1076"}}, "ref-authors": {"author": [{"@seq": "1", "ce:initials": "K.L.", "@_fa": "true", "ce:surname": "Andereck", "ce:indexed-name": "Andereck K.L."}, {"@seq": "2", "ce:initials": "K.M.", "@_fa": "true", "ce:surname": "Valentine", "ce:indexed-name": "Valentine K.M."}, {"@seq": "3", "ce:initials": "R.C.", "@_fa": "true", "ce:surname": "Knopf", "ce:indexed-name": "Knopf R.C."}, {"@seq": "4", "ce:initials": "C.A.", "@_fa": "true", "ce:surname": "Vogt", "ce:indexed-name": "Vogt C.A."}]}, "ref-sourcetitle": "Annals of Tourism Research"}}, {"ref-fulltext": "R.T.Boonmathya, (2003). A narrative of contested views of development in Thai society: Voices of villager in Northeastern Thailand. Southeast Asian Studies, 41(3), 269\u2013298.", "@id": "3", "ref-info": {"ref-publicationyear": {"@first": "2003"}, "ref-title": {"ref-titletext": "A narrative of contested views of development in Thai society: Voices of villager in Northeastern Thailand"}, "refd-itemidlist": {"itemid": {"$": "1842483834", "@idtype": "SGR"}}, "ref-volisspag": {"voliss": {"@volume": "41", "@issue": "3"}, "pagerange": {"@first": "269", "@last": "298"}}, "ref-authors": {"author": [{"@seq": "1", "ce:initials": "R.T.", "@_fa": "true", "ce:surname": "Boonmathya", "ce:indexed-name": "Boonmathya R.T."}]}, "ref-sourcetitle": "Southeast Asian Studies"}}, {"ref-fulltext": "P.J.Boyle,, K.H.Halfacree,, & V.Robinson, (1998). Exploring contemporary migration. Harlow: Longman.", "@id": "4", "ref-info": {"ref-publicationyear": {"@first": "1998"}, "refd-itemidlist": {"itemid": {"$": "0004269937", "@idtype": "SGR"}}, "ref-text": "Harlow: Longman", "ref-authors": {"author": [{"@seq": "1", "ce:initials": "P.J.", "@_fa": "true", "ce:surname": "Boyle", "ce:indexed-name": "Boyle P.J."}, {"@seq": "2", "ce:initials": "K.H.", "@_fa": "true", "ce:surname": "Halfacree", "ce:indexed-name": "Halfacree K.H."}, {"@seq": "3", "ce:initials": "V.", "@_fa": "true", "ce:surname": "Robinson", "ce:indexed-name": "Robinson V."}]}, "ref-sourcetitle": "Exploring contemporary migration"}}, {"ref-fulltext": "J.Brewer, (2000). Ethnography. Buckingham: OUP.", "@id": "5", "ref-info": {"ref-publicationyear": {"@first": "2000"}, "refd-itemidlist": {"itemid": {"$": "37149043972", "@idtype": "SGR"}}, "ref-text": "Buckingham: OUP", "ref-authors": {"author": [{"@seq": "1", "ce:initials": "J.", "@_fa": "true", "ce:surname": "Brewer", "ce:indexed-name": "Brewer J."}]}, "ref-sourcetitle": "Ethnography"}}, {"ref-fulltext": "J.Brougham,, & R.Butler, (1981). A segmentation analysis of resident attitudes to the social impacts of tourism. Annals of Tourism Research, 8(4), 569\u2013590. doi: 10.1016/0160-7383(81)90042-6", "@id": "6", "ref-info": {"ref-publicationyear": {"@first": "1981"}, "ref-title": {"ref-titletext": "A segmentation analysis of resident attitudes to the social impacts of tourism"}, "refd-itemidlist": {"itemid": {"$": "0019661063", "@idtype": "SGR"}}, "ref-volisspag": {"voliss": {"@volume": "8", "@issue": "4"}, "pagerange": {"@first": "569", "@last": "590"}}, "ref-authors": {"author": [{"@seq": "1", "ce:initials": "J.", "@_fa": "true", "ce:surname": "Brougham", "ce:indexed-name": "Brougham J."}, {"@seq": "2", "ce:initials": "R.", "@_fa": "true", "ce:surname": "Butler", "ce:indexed-name": "Butler R."}]}, "ref-sourcetitle": "Annals of Tourism Research"}}, {"ref-fulltext": "A.Bryman, (2004). Social research methods. Oxford: Oxford University Press.", "@id": "7", "ref-info": {"ref-publicationyear": {"@first": "2004"}, "refd-itemidlist": {"itemid": {"$": "0003624734", "@idtype": "SGR"}}, "ref-text": "Oxford: Oxford University Press", "ref-authors": {"author": [{"@seq": "1", "ce:initials": "A.", "@_fa": "true", "ce:surname": "Bryman", "ce:indexed-name": "Bryman A."}]}, "ref-sourcetitle": "Social research methods"}}, {"ref-fulltext": "R.W.Butler, (1980). The concept of a tourist area lifecycle of evolution: Implications for management of resources. Canadian Geographer, 24(1), 5\u201312. doi: 10.1111/j.1541-0064.1980.tb00970.x", "@id": "8", "ref-info": {"ref-publicationyear": {"@first": "1980"}, "ref-title": {"ref-titletext": "The concept of a tourist area lifecycle of evolution: Implications for management of resources"}, "refd-itemidlist": {"itemid": {"$": "0018917460", "@idtype": "SGR"}}, "ref-volisspag": {"voliss": {"@volume": "24", "@issue": "1"}, "pagerange": {"@first": "5", "@last": "12"}}, "ref-authors": {"author": [{"@seq": "1", "ce:initials": "R.W.", "@_fa": "true", "ce:surname": "Butler", "ce:indexed-name": "Butler R.W."}]}, "ref-sourcetitle": "Canadian Geographer"}}, {"ref-fulltext": "B.A.Carmichael, (2000). A matrix model for resident attitudes and behaviours in a rapidly changing tourist area. Tourism Management, 21, 601\u2013611. doi: 10.1016/S0261-5177(00)00007-8", "@id": "9", "ref-info": {"ref-publicationyear": {"@first": "2000"}, "ref-title": {"ref-titletext": "A matrix model for resident attitudes and behaviours in a rapidly changing tourist area"}, "refd-itemidlist": {"itemid": {"$": "0034091319", "@idtype": "SGR"}}, "ref-volisspag": {"voliss": {"@volume": "21"}, "pagerange": {"@first": "601", "@last": "611"}}, "ref-authors": {"author": [{"@seq": "1", "ce:initials": "B.A.", "@_fa": "true", "ce:surname": "Carmichael", "ce:indexed-name": "Carmichael B.A."}]}, "ref-sourcetitle": "Tourism Management"}}, {"ref-fulltext": "Y.Chalamwong, (2001). Recent trends in migration flows and policies in Thailand. TDRI Quarterly Review, 16(2), 10\u201318.", "@id": "10", "ref-info": {"ref-publicationyear": {"@first": "2001"}, "ref-title": {"ref-titletext": "Recent trends in migration flows and policies in Thailand"}, "refd-itemidlist": {"itemid": {"$": "34249328295", "@idtype": "SGR"}}, "ref-volisspag": {"voliss": {"@volume": "16", "@issue": "2"}, "pagerange": {"@first": "10", "@last": "18"}}, "ref-authors": {"author": [{"@seq": "1", "ce:initials": "Y.", "@_fa": "true", "ce:surname": "Chalamwong", "ce:indexed-name": "Chalamwong Y."}]}, "ref-sourcetitle": "TDRI Quarterly Review"}}, {"ref-fulltext": "E.Cohen, (1982). Thai girls and Farang men the edge of ambiguity. Annals of Tourism Research, 9(3), 403\u2013428. doi: 10.1016/0160-7383(82)90021-4", "@id": "11", "ref-info": {"ref-publicationyear": {"@first": "1982"}, "ref-title": {"ref-titletext": "Thai girls and Farang men the edge of ambiguity"}, "refd-itemidlist": {"itemid": {"$": "0020372450", "@idtype": "SGR"}}, "ref-volisspag": {"voliss": {"@volume": "9", "@issue": "3"}, "pagerange": {"@first": "403", "@last": "428"}}, "ref-authors": {"author": [{"@seq": "1", "ce:initials": "E.", "@_fa": "true", "ce:surname": "Cohen", "ce:indexed-name": "Cohen E."}]}, "ref-sourcetitle": "Annals of Tourism Research"}}, {"ref-fulltext": "I.Coxhead,, & J.Plangpraphan, (1999). Economic boom, financial bust, and the decline of Thai agriculture: Was growth in the 1990s too fast? Chulalongkorn Journal of Economics, 11(1), 1\u201318.", "@id": "12", "ref-info": {"ref-publicationyear": {"@first": "1999"}, "ref-title": {"ref-titletext": "Economic boom, financial bust, and the decline of Thai agriculture: Was growth in the 1990s too fast?"}, "refd-itemidlist": {"itemid": {"$": "0004455558", "@idtype": "SGR"}}, "ref-volisspag": {"voliss": {"@volume": "11", "@issue": "1"}, "pagerange": {"@first": "1", "@last": "18"}}, "ref-authors": {"author": [{"@seq": "1", "ce:initials": "I.", "@_fa": "true", "ce:surname": "Coxhead", "ce:indexed-name": "Coxhead I."}, {"@seq": "2", "ce:initials": "J.", "@_fa": "true", "ce:surname": "Plangpraphan", "ce:indexed-name": "Plangpraphan J."}]}, "ref-sourcetitle": "Chulalongkorn Journal of Economics"}}, {"ref-fulltext": "J.Croall, (1995). Preserve or destroy: Tourism and the environment. London: Calouste Gulbenkian Foundation.", "@id": "13", "ref-info": {"ref-publicationyear": {"@first": "1995"}, "refd-itemidlist": {"itemid": {"$": "0004299054", "@idtype": "SGR"}}, "ref-text": "London: Calouste Gulbenkian Foundation", "ref-authors": {"author": [{"@seq": "1", "ce:initials": "J.", "@_fa": "true", "ce:surname": "Croall", "ce:indexed-name": "Croall J."}]}, "ref-sourcetitle": "Preserve or destroy: Tourism and the environment"}}, {"ref-fulltext": "A.Dang,, S.Goldstein,, & J.McNally, (1997). Internal migration and development in Vietnam. International Migration Review, 31(2), 312\u2013337. doi: 10.2307/2547222", "@id": "14", "ref-info": {"ref-publicationyear": {"@first": "1997"}, "ref-title": {"ref-titletext": "Internal migration and development in Vietnam"}, "refd-itemidlist": {"itemid": {"$": "0000941169", "@idtype": "SGR"}}, "ref-volisspag": {"voliss": {"@volume": "31", "@issue": "2"}, "pagerange": {"@first": "312", "@last": "337"}}, "ref-authors": {"author": [{"@seq": "1", "ce:initials": "A.", "@_fa": "true", "ce:surname": "Dang", "ce:indexed-name": "Dang A."}, {"@seq": "2", "ce:initials": "S.", "@_fa": "true", "ce:surname": "Goldstein", "ce:indexed-name": "Goldstein S."}, {"@seq": "3", "ce:initials": "J.", "@_fa": "true", "ce:surname": "McNally", "ce:indexed-name": "McNally J."}]}, "ref-sourcetitle": "International Migration Review"}}, {"ref-fulltext": "D.Davis,, J.Allen,, & R.M.Cosenza, (1988). Segmenting local residents by their attitudes, interests, and opinions toward tourism. Journal of Travel Research, 27(2), 2\u20138. doi: 10.1177/004728758802700201", "@id": "15", "ref-info": {"ref-publicationyear": {"@first": "1988"}, "ref-title": {"ref-titletext": "Segmenting local residents by their attitudes, interests, and opinions toward tourism"}, "refd-itemidlist": {"itemid": {"$": "0024189056", "@idtype": "SGR"}}, "ref-volisspag": {"voliss": {"@volume": "27", "@issue": "2"}, "pagerange": {"@first": "2", "@last": "8"}}, "ref-authors": {"author": [{"@seq": "1", "ce:initials": "D.", "@_fa": "true", "ce:surname": "Davis", "ce:indexed-name": "Davis D."}, {"@seq": "2", "ce:initials": "J.", "@_fa": "true", "ce:surname": "Allen", "ce:indexed-name": "Allen J."}, {"@seq": "3", "ce:initials": "R.M.", "@_fa": "true", "ce:surname": "Cosenza", "ce:indexed-name": "Cosenza R.M."}]}, "ref-sourcetitle": "Journal of Travel Research"}}, {"ref-fulltext": "N.Denzin,, & Y.S.Lincoln, (2000). The Sage handbook of qualitative research (2nd ed.). London: Sage.", "@id": "16", "ref-info": {"ref-publicationyear": {"@first": "2000"}, "refd-itemidlist": {"itemid": {"$": "0003874262", "@idtype": "SGR"}}, "ref-text": "2nd ed., London: Sage", "ref-authors": {"author": [{"@seq": "1", "ce:initials": "N.", "@_fa": "true", "ce:surname": "Denzin", "ce:indexed-name": "Denzin N."}, {"@seq": "2", "ce:initials": "Y.S.", "@_fa": "true", "ce:surname": "Lincoln", "ce:indexed-name": "Lincoln Y.S."}]}, "ref-sourcetitle": "The Sage handbook of qualitative research"}}, {"ref-fulltext": "T.R.Evans, (1993). Residents\u2019 perceptions of tourism in selected New Zealand communities: A segmentation study (Unpublished master thesis). Otago University, New Zealand.", "@id": "17", "ref-info": {"ref-publicationyear": {"@first": "1993"}, "refd-itemidlist": {"itemid": {"$": "84943457454", "@idtype": "SGR"}}, "ref-text": "Residents\u2019 perceptions of tourism in selected New Zealand communities: A segmentation study (Unpublished master thesis). Otago University, New Zealand", "ref-authors": {"author": [{"@seq": "1", "ce:initials": "T.R.", "@_fa": "true", "ce:surname": "Evans", "ce:indexed-name": "Evans T.R."}]}}}, {"ref-fulltext": "E.Fredline,, & B.Faulkner, (2000). Host community reactions: A cluster analysis. Annals of Tourism Research, 27(3), 763\u2013784. doi: 10.1016/S0160-7383(99)00103-6", "@id": "18", "ref-info": {"ref-publicationyear": {"@first": "2000"}, "ref-title": {"ref-titletext": "Host community reactions: A cluster analysis"}, "refd-itemidlist": {"itemid": {"$": "0034009043", "@idtype": "SGR"}}, "ref-volisspag": {"voliss": {"@volume": "27", "@issue": "3"}, "pagerange": {"@first": "763", "@last": "784"}}, "ref-authors": {"author": [{"@seq": "1", "ce:initials": "E.", "@_fa": "true", "ce:surname": "Fredline", "ce:indexed-name": "Fredline E."}, {"@seq": "2", "ce:initials": "B.", "@_fa": "true", "ce:surname": "Faulkner", "ce:indexed-name": "Faulkner B."}]}, "ref-sourcetitle": "Annals of Tourism Research"}}, {"ref-fulltext": "T.D.Fuller, (1981). Migrant-native socio-economic differentials in Thailand. Demography, 18(1), 55\u201366. doi: 10.2307/2061049", "@id": "19", "ref-info": {"ref-publicationyear": {"@first": "1981"}, "ref-title": {"ref-titletext": "Migrant-native socio-economic differentials in Thailand"}, "refd-itemidlist": {"itemid": {"$": "0019531367", "@idtype": "SGR"}}, "ref-volisspag": {"voliss": {"@volume": "18", "@issue": "1"}, "pagerange": {"@first": "55", "@last": "66"}}, "ref-authors": {"author": [{"@seq": "1", "ce:initials": "T.D.", "@_fa": "true", "ce:surname": "Fuller", "ce:indexed-name": "Fuller T.D."}]}, "ref-sourcetitle": "Demography"}}, {"ref-fulltext": "T.D.Fuller,, P.Lightfoot,, & P.Kamnuansilpa, (1985). Rural-urban mobility in Thailand: A decision-making approach. Demography, 22(4), 565\u2013579. doi: 10.2307/2061588", "@id": "20", "ref-info": {"ref-publicationyear": {"@first": "1985"}, "ref-title": {"ref-titletext": "Rural-urban mobility in Thailand: A decision-making approach"}, "refd-itemidlist": {"itemid": {"$": "0022155293", "@idtype": "SGR"}}, "ref-volisspag": {"voliss": {"@volume": "22", "@issue": "4"}, "pagerange": {"@first": "565", "@last": "579"}}, "ref-authors": {"author": [{"@seq": "1", "ce:initials": "T.D.", "@_fa": "true", "ce:surname": "Fuller", "ce:indexed-name": "Fuller T.D."}, {"@seq": "2", "ce:initials": "P.", "@_fa": "true", "ce:surname": "Lightfoot", "ce:indexed-name": "Lightfoot P."}, {"@seq": "3", "ce:initials": "P.", "@_fa": "true", "ce:surname": "Kamnuansilpa", "ce:indexed-name": "Kamnuansilpa P."}]}, "ref-sourcetitle": "Demography"}}, {"ref-fulltext": "O.Gjerald, (2005). Socio-cultural impacts of tourism: A case study from Norway. Journal of Tourism and Cultural Change, 3(1), 36\u201358. doi: 10.1080/14766820508669095", "@id": "21", "ref-info": {"ref-publicationyear": {"@first": "2005"}, "ref-title": {"ref-titletext": "Socio-cultural impacts of tourism: A case study from Norway"}, "refd-itemidlist": {"itemid": {"$": "85008827405", "@idtype": "SGR"}}, "ref-volisspag": {"voliss": {"@volume": "3", "@issue": "1"}, "pagerange": {"@first": "36", "@last": "58"}}, "ref-authors": {"author": [{"@seq": "1", "ce:initials": "O.", "@_fa": "true", "ce:surname": "Gjerald", "ce:indexed-name": "Gjerald O."}]}, "ref-sourcetitle": "Journal of Tourism and Cultural Change"}}, {"ref-fulltext": "E.Guba, (1990). The paradigm dialogue. Newbury Park, CA: Sage.", "@id": "22", "ref-info": {"ref-publicationyear": {"@first": "1990"}, "refd-itemidlist": {"itemid": {"$": "0004263511", "@idtype": "SGR"}}, "ref-text": "Newbury Park, CA: Sage", "ref-authors": {"author": [{"@seq": "1", "ce:initials": "E.", "@_fa": "true", "ce:surname": "Guba", "ce:indexed-name": "Guba E."}]}, "ref-sourcetitle": "The paradigm dialogue"}}, {"ref-fulltext": "E.G.Guba,, & Y.S.Lincoln, (1985). Naturalistic inquiry. Beverly Hills, CA: Sage.", "@id": "23", "ref-info": {"ref-publicationyear": {"@first": "1985"}, "refd-itemidlist": {"itemid": {"$": "0004253047", "@idtype": "SGR"}}, "ref-text": "Beverly Hills, CA: Sage", "ref-authors": {"author": [{"@seq": "1", "ce:initials": "E.G.", "@_fa": "true", "ce:surname": "Guba", "ce:indexed-name": "Guba E.G."}, {"@seq": "2", "ce:initials": "Y.S.", "@_fa": "true", "ce:surname": "Lincoln", "ce:indexed-name": "Lincoln Y.S."}]}, "ref-sourcetitle": "Naturalistic inquiry"}}, {"ref-fulltext": "C.M.Hall,, & S.Page, (2002). The geography of tourism and recreation: Environment, place and space (2nd ed.). London: Routledge.", "@id": "24", "ref-info": {"ref-publicationyear": {"@first": "2002"}, "refd-itemidlist": {"itemid": {"$": "0011189059", "@idtype": "SGR"}}, "ref-text": "2nd ed., London: Routledge", "ref-authors": {"author": [{"@seq": "1", "ce:initials": "C.M.", "@_fa": "true", "ce:surname": "Hall", "ce:indexed-name": "Hall C.M."}, {"@seq": "2", "ce:initials": "S.", "@_fa": "true", "ce:surname": "Page", "ce:indexed-name": "Page S."}]}, "ref-sourcetitle": "The geography of tourism and recreation: Environment, place and space"}}, {"ref-fulltext": "S.A.Hernandez,, J.Cohen,, & H.L.Garcia, (1996). Residents\u2019 attitudes towards an instant resort enclave. Annals of Tourism Research, 23(4), 755\u2013779. doi: 10.1016/0160-7383(95)00114-X", "@id": "25", "ref-info": {"ref-publicationyear": {"@first": "1996"}, "ref-title": {"ref-titletext": "Residents\u2019 attitudes towards an instant resort enclave"}, "refd-itemidlist": {"itemid": {"$": "0030441143", "@idtype": "SGR"}}, "ref-volisspag": {"voliss": {"@volume": "23", "@issue": "4"}, "pagerange": {"@first": "755", "@last": "779"}}, "ref-authors": {"author": [{"@seq": "1", "ce:initials": "S.A.", "@_fa": "true", "ce:surname": "Hernandez", "ce:indexed-name": "Hernandez S.A."}, {"@seq": "2", "ce:initials": "J.", "@_fa": "true", "ce:surname": "Cohen", "ce:indexed-name": "Cohen J."}, {"@seq": "3", "ce:initials": "H.L.", "@_fa": "true", "ce:surname": "Garcia", "ce:indexed-name": "Garcia H.L."}]}, "ref-sourcetitle": "Annals of Tourism Research"}}, {"ref-fulltext": "C.Hesse-Swain, (2006). Programming beauty and the absence of Na Lao: Popular Thai TV and identity formation among youth in Northeast Thailand. Geographic Journal, 66, 257\u2013272.", "@id": "26", "ref-info": {"ref-publicationyear": {"@first": "2006"}, "ref-title": {"ref-titletext": "Programming beauty and the absence of Na Lao: Popular Thai TV and identity formation among youth in Northeast Thailand"}, "refd-itemidlist": {"itemid": {"$": "33751182610", "@idtype": "SGR"}}, "ref-volisspag": {"voliss": {"@volume": "66"}, "pagerange": {"@first": "257", "@last": "272"}}, "ref-authors": {"author": [{"@seq": "1", "ce:initials": "C.", "@_fa": "true", "ce:surname": "Hesse-Swain", "ce:indexed-name": "Hesse-Swain C."}]}, "ref-sourcetitle": "Geographic Journal"}}, {"ref-fulltext": "A.Holden, (2000). Environment and tourism. London: Routledge.", "@id": "27", "ref-info": {"ref-publicationyear": {"@first": "2000"}, "refd-itemidlist": {"itemid": {"$": "0011714954", "@idtype": "SGR"}}, "ref-text": "London: Routledge", "ref-authors": {"author": [{"@seq": "1", "ce:initials": "A.", "@_fa": "true", "ce:surname": "Holden", "ce:indexed-name": "Holden A."}]}, "ref-sourcetitle": "Environment and tourism"}}, {"ref-fulltext": "M.S.Jackson,, & R.J.Inbakaran, (2006). Evaluating residents\u2019 attitudes and intentions to act towards tourism development in regional Victoria, Australia. International Journal of Tourism Research, 8, 355\u2013366. doi: 10.1002/jtr.584", "@id": "28", "ref-info": {"ref-publicationyear": {"@first": "2006"}, "ref-title": {"ref-titletext": "Evaluating residents\u2019 attitudes and intentions to act towards tourism development in regional Victoria, Australia"}, "refd-itemidlist": {"itemid": {"$": "58149480602", "@idtype": "SGR"}}, "ref-volisspag": {"voliss": {"@volume": "8"}, "pagerange": {"@first": "355", "@last": "366"}}, "ref-authors": {"author": [{"@seq": "1", "ce:initials": "M.S.", "@_fa": "true", "ce:surname": "Jackson", "ce:indexed-name": "Jackson M.S."}, {"@seq": "2", "ce:initials": "R.J.", "@_fa": "true", "ce:surname": "Inbakaran", "ce:indexed-name": "Inbakaran R.J."}]}, "ref-sourcetitle": "International Journal of Tourism Research"}}, {"ref-fulltext": "J.Jafari, (1973). The role of tourism in the socio-economic transformation of developing countries (Unpublished master thesis). Cornell University, Ithaca, NY.", "@id": "29", "ref-info": {"ref-publicationyear": {"@first": "1973"}, "refd-itemidlist": {"itemid": {"$": "84943456878", "@idtype": "SGR"}}, "ref-text": "The role of tourism in the socio-economic transformation of developing countries (Unpublished master thesis). Cornell University, Ithaca, NY", "ref-authors": {"author": [{"@seq": "1", "ce:initials": "J.", "@_fa": "true", "ce:surname": "Jafari", "ce:indexed-name": "Jafari J."}]}}}, {"ref-fulltext": "C.F.Keyes, (1967). Isan: Regionalism in Northeastern Thailand. Ithaca, NY: Cornell University.", "@id": "30", "ref-info": {"ref-publicationyear": {"@first": "1967"}, "refd-itemidlist": {"itemid": {"$": "0039612446", "@idtype": "SGR"}}, "ref-text": "Ithaca, NY: Cornell University", "ref-authors": {"author": [{"@seq": "1", "ce:initials": "C.F.", "@_fa": "true", "ce:surname": "Keyes", "ce:indexed-name": "Keyes C.F."}]}, "ref-sourcetitle": "Isan: Regionalism in Northeastern Thailand"}}, {"ref-fulltext": "B.King,, A.Pizam,, & A.Milman, (1993). Social impacts of tourism: Hosts perceptions. Annals of Tourism Research, 20(4), 650\u2013665. doi: 10.1016/0160-7383(93)90089-L", "@id": "31", "ref-info": {"ref-publicationyear": {"@first": "1993"}, "ref-title": {"ref-titletext": "Social impacts of tourism: Hosts perceptions"}, "refd-itemidlist": {"itemid": {"$": "0027713899", "@idtype": "SGR"}}, "ref-volisspag": {"voliss": {"@volume": "20", "@issue": "4"}, "pagerange": {"@first": "650", "@last": "665"}}, "ref-authors": {"author": [{"@seq": "1", "ce:initials": "B.", "@_fa": "true", "ce:surname": "King", "ce:indexed-name": "King B."}, {"@seq": "2", "ce:initials": "A.", "@_fa": "true", "ce:surname": "Pizam", "ce:indexed-name": "Pizam A."}, {"@seq": "3", "ce:initials": "A.", "@_fa": "true", "ce:surname": "Milman", "ce:indexed-name": "Milman A."}]}, "ref-sourcetitle": "Annals of Tourism Research"}}, {"ref-fulltext": "A.Kislenko, (2004). Culture and customs of Thailand. London: Greenwood Press.", "@id": "32", "ref-info": {"ref-publicationyear": {"@first": "2004"}, "refd-itemidlist": {"itemid": {"$": "77955645995", "@idtype": "SGR"}}, "ref-text": "London: Greenwood Press", "ref-authors": {"author": [{"@seq": "1", "ce:initials": "A.", "@_fa": "true", "ce:surname": "Kislenko", "ce:indexed-name": "Kislenko A."}]}, "ref-sourcetitle": "Culture and customs of Thailand"}}, {"ref-fulltext": "P.Kitiarsa, (2006). Village transnationalism: Transborder identities among Thai-Isan migrant workers in Singapore (Working Paper Series 71). Asia Research Institute, National University of Singapore.", "@id": "33", "ref-info": {"ref-publicationyear": {"@first": "2006"}, "refd-itemidlist": {"itemid": {"$": "84943453667", "@idtype": "SGR"}}, "ref-text": "Village transnationalism: Transborder identities among Thai-Isan migrant workers in Singapore (Working Paper Series 71). Asia Research Institute, National University of Singapore", "ref-authors": {"author": [{"@seq": "1", "ce:initials": "P.", "@_fa": "true", "ce:surname": "Kitiarsa", "ce:indexed-name": "Kitiarsa P."}]}}}, {"ref-fulltext": "W.J.Klausner, (1993). Reflections on Thai culture. Bangkok: Sayam Samakhom.", "@id": "34", "ref-info": {"ref-publicationyear": {"@first": "1993"}, "refd-itemidlist": {"itemid": {"$": "0003960589", "@idtype": "SGR"}}, "ref-text": "Bangkok: Sayam Samakhom", "ref-authors": {"author": [{"@seq": "1", "ce:initials": "W.J.", "@_fa": "true", "ce:surname": "Klausner", "ce:indexed-name": "Klausner W.J."}]}, "ref-sourcetitle": "Reflections on Thai culture"}}, {"ref-fulltext": "S.Konim, (1990). Psychology of the Thai people: Values and behaviour patterns. Bangkok: Research Centre, NIDA.", "@id": "35", "ref-info": {"ref-publicationyear": {"@first": "1990"}, "refd-itemidlist": {"itemid": {"$": "84912034533", "@idtype": "SGR"}}, "ref-text": "Bangkok: Research Centre, NIDA", "ref-authors": {"author": [{"@seq": "1", "ce:initials": "S.", "@_fa": "true", "ce:surname": "Konim", "ce:indexed-name": "Konim S."}]}, "ref-sourcetitle": "Psychology of the Thai people: Values and behaviour patterns"}}, {"ref-fulltext": "K.Korinek,, B.Entwisle,, & A.Jampaklay, (2005). Through thick and thin: Layers of social ties and urban settlement among Thai migrants. American Sociological Review, 70(5), 779\u2013800. doi: 10.1177/000312240507000503", "@id": "36", "ref-info": {"ref-publicationyear": {"@first": "2005"}, "ref-title": {"ref-titletext": "Through thick and thin: Layers of social ties and urban settlement among Thai migrants"}, "refd-itemidlist": {"itemid": {"$": "30444432747", "@idtype": "SGR"}}, "ref-volisspag": {"voliss": {"@volume": "70", "@issue": "5"}, "pagerange": {"@first": "779", "@last": "800"}}, "ref-authors": {"author": [{"@seq": "1", "ce:initials": "K.", "@_fa": "true", "ce:surname": "Korinek", "ce:indexed-name": "Korinek K."}, {"@seq": "2", "ce:initials": "B.", "@_fa": "true", "ce:surname": "Entwisle", "ce:indexed-name": "Entwisle B."}, {"@seq": "3", "ce:initials": "A.", "@_fa": "true", "ce:surname": "Jampaklay", "ce:indexed-name": "Jampaklay A."}]}, "ref-sourcetitle": "American Sociological Review"}}, {"ref-fulltext": "Y.Kuvan,, & P.Akan, (2004). Residents\u2019 attitudes toward general and forest-related impacts of tourism: The case of Belek, Antalya. Tourism Management, 26, 691\u2013706. doi: 10.1016/j.tourman.2004.02.019", "@id": "37", "ref-info": {"ref-publicationyear": {"@first": "2004"}, "ref-title": {"ref-titletext": "Residents\u2019 attitudes toward general and forest-related impacts of tourism: The case of Belek, Antalya"}, "refd-itemidlist": {"itemid": {"$": "20544451517", "@idtype": "SGR"}}, "ref-volisspag": {"voliss": {"@volume": "26"}, "pagerange": {"@first": "691", "@last": "706"}}, "ref-authors": {"author": [{"@seq": "1", "ce:initials": "Y.", "@_fa": "true", "ce:surname": "Kuvan", "ce:indexed-name": "Kuvan Y."}, {"@seq": "2", "ce:initials": "P.", "@_fa": "true", "ce:surname": "Akan", "ce:indexed-name": "Akan P."}]}, "ref-sourcetitle": "Tourism Management"}}, {"ref-fulltext": "T.J.Lee,, J.Li,, & H.-K.Kim, (2007). Community residents\u2019 perceptions and attitudes towards heritage tourism in a historic city. Tourism and Hospitality Planning and Development, 4(2), 91\u2013109. doi: 10.1080/14790530701554124", "@id": "38", "ref-info": {"ref-publicationyear": {"@first": "2007"}, "ref-title": {"ref-titletext": "Community residents\u2019 perceptions and attitudes towards heritage tourism in a historic city"}, "refd-itemidlist": {"itemid": {"$": "84864683315", "@idtype": "SGR"}}, "ref-volisspag": {"voliss": {"@volume": "4", "@issue": "2"}, "pagerange": {"@first": "91", "@last": "109"}}, "ref-authors": {"author": [{"@seq": "1", "ce:initials": "T.J.", "@_fa": "true", "ce:surname": "Lee", "ce:indexed-name": "Lee T.J."}, {"@seq": "2", "ce:initials": "J.", "@_fa": "true", "ce:surname": "Li", "ce:indexed-name": "Li J."}, {"@seq": "3", "ce:initials": "H.-K.", "@_fa": "true", "ce:surname": "Kim", "ce:indexed-name": "Kim H.-K."}]}, "ref-sourcetitle": "Tourism and Hospitality Planning and Development"}}, {"ref-fulltext": "A.Lepp, (2006). Residents\u2019 attitudes towards tourism in Bigodi village, Uganda. Tourism Management, 28, 876\u2013885. doi: 10.1016/j.tourman.2006.03.004", "@id": "39", "ref-info": {"ref-publicationyear": {"@first": "2006"}, "ref-title": {"ref-titletext": "Residents\u2019 attitudes towards tourism in Bigodi village, Uganda"}, "refd-itemidlist": {"itemid": {"$": "39049084609", "@idtype": "SGR"}}, "ref-volisspag": {"voliss": {"@volume": "28"}, "pagerange": {"@first": "876", "@last": "885"}}, "ref-authors": {"author": [{"@seq": "1", "ce:initials": "A.", "@_fa": "true", "ce:surname": "Lepp", "ce:indexed-name": "Lepp A."}]}, "ref-sourcetitle": "Tourism Management"}}, {"ref-fulltext": "L.Malam, (2003). Performing masculinity on the Thai beach scene (Working Paper No. 8). Australia: Gender Relations Centre.", "@id": "40", "ref-info": {"ref-publicationyear": {"@first": "2003"}, "refd-itemidlist": {"itemid": {"$": "84943454046", "@idtype": "SGR"}}, "ref-text": "Performing masculinity on the Thai beach scene (Working Paper No. 8). Australia: Gender Relations Centre", "ref-authors": {"author": [{"@seq": "1", "ce:initials": "L.", "@_fa": "true", "ce:surname": "Malam", "ce:indexed-name": "Malam L."}]}}}, {"ref-fulltext": "P.Mason, (2003). Tourism impacts, planning and management. Oxford: Butterworth-Heinemann.", "@id": "41", "ref-info": {"ref-publicationyear": {"@first": "2003"}, "refd-itemidlist": {"itemid": {"$": "4143079643", "@idtype": "SGR"}}, "ref-text": "Oxford: Butterworth-Heinemann", "ref-authors": {"author": [{"@seq": "1", "ce:initials": "P.", "@_fa": "true", "ce:surname": "Mason", "ce:indexed-name": "Mason P."}]}, "ref-sourcetitle": "Tourism impacts, planning and management"}}, {"ref-fulltext": "A.Mathieson,, & G.Wall, (2006). Tourism: Changes, impacts and opportunities. Harlow: Pearson Prentice Hall.", "@id": "42", "ref-info": {"ref-publicationyear": {"@first": "2006"}, "refd-itemidlist": {"itemid": {"$": "33750980152", "@idtype": "SGR"}}, "ref-text": "Harlow: Pearson Prentice Hall", "ref-authors": {"author": [{"@seq": "1", "ce:initials": "A.", "@_fa": "true", "ce:surname": "Mathieson", "ce:indexed-name": "Mathieson A."}, {"@seq": "2", "ce:initials": "G.", "@_fa": "true", "ce:surname": "Wall", "ce:indexed-name": "Wall G."}]}, "ref-sourcetitle": "Tourism: Changes, impacts and opportunities"}}, {"ref-fulltext": "E.Maticka-Tyndale,, D.Elkins,, M.H.Elkins,, D.Rujkarakorn,, T.Kuyyakanond,, & K.Stam, (1997). Contexts and patterns of men's commercial sexual partnerships in Northeastern Thailand: Implications for AIDS prevention. Social Science Medicine, 44(2), 199\u2013213. doi: 10.1016/S0277-9536(96)00146-3", "@id": "43", "ref-info": {"ref-publicationyear": {"@first": "1997"}, "ref-title": {"ref-titletext": "Contexts and patterns of men's commercial sexual partnerships in Northeastern Thailand: Implications for AIDS prevention"}, "refd-itemidlist": {"itemid": {"$": "0030617927", "@idtype": "SGR"}}, "ref-volisspag": {"voliss": {"@volume": "44", "@issue": "2"}, "pagerange": {"@first": "199", "@last": "213"}}, "ref-authors": {"author": [{"@seq": "1", "ce:initials": "E.", "@_fa": "true", "ce:surname": "Maticka-Tyndale", "ce:indexed-name": "Maticka-Tyndale E."}, {"@seq": "2", "ce:initials": "D.", "@_fa": "true", "ce:surname": "Elkins", "ce:indexed-name": "Elkins D."}, {"@seq": "3", "ce:initials": "M.H.", "@_fa": "true", "ce:surname": "Elkins", "ce:indexed-name": "Elkins M.H."}, {"@seq": "4", "ce:initials": "D.", "@_fa": "true", "ce:surname": "Rujkarakorn", "ce:indexed-name": "Rujkarakorn D."}, {"@seq": "5", "ce:initials": "T.", "@_fa": "true", "ce:surname": "Kuyyakanond", "ce:indexed-name": "Kuyyakanond T."}, {"@seq": "6", "ce:initials": "K.", "@_fa": "true", "ce:surname": "Stam", "ce:indexed-name": "Stam K."}]}, "ref-sourcetitle": "Social Science Medicine"}}, {"ref-fulltext": "S.McCool,, & S.Martin, (1994). Community attachment and attitudes towards tourism development. Journal of Travel Research, 32(3), 29\u201334. doi: 10.1177/004728759403200305", "@id": "44", "ref-info": {"ref-publicationyear": {"@first": "1994"}, "ref-title": {"ref-titletext": "Community attachment and attitudes towards tourism development"}, "refd-itemidlist": {"itemid": {"$": "0028006962", "@idtype": "SGR"}}, "ref-volisspag": {"voliss": {"@volume": "32", "@issue": "3"}, "pagerange": {"@first": "29", "@last": "34"}}, "ref-authors": {"author": [{"@seq": "1", "ce:initials": "S.", "@_fa": "true", "ce:surname": "McCool", "ce:indexed-name": "McCool S."}, {"@seq": "2", "ce:initials": "S.", "@_fa": "true", "ce:surname": "Martin", "ce:indexed-name": "Martin S."}]}, "ref-sourcetitle": "Journal of Travel Research"}}, {"ref-fulltext": "A.Milman,, & A.Pizam, (1988). Social impacts of tourism on central Florida. Annals of Tourism Research, 15(2), 191\u2013204. doi: 10.1016/0160-7383(88)90082-5", "@id": "45", "ref-info": {"ref-publicationyear": {"@first": "1988"}, "ref-title": {"ref-titletext": "Social impacts of tourism on central Florida"}, "refd-itemidlist": {"itemid": {"$": "0024155884", "@idtype": "SGR"}}, "ref-volisspag": {"voliss": {"@volume": "15", "@issue": "2"}, "pagerange": {"@first": "191", "@last": "204"}}, "ref-authors": {"author": [{"@seq": "1", "ce:initials": "A.", "@_fa": "true", "ce:surname": "Milman", "ce:indexed-name": "Milman A."}, {"@seq": "2", "ce:initials": "A.", "@_fa": "true", "ce:surname": "Pizam", "ce:indexed-name": "Pizam A."}]}, "ref-sourcetitle": "Annals of Tourism Research"}}, {"ref-fulltext": "S.Peracca,, J.Knodel,, & C.Saengtienchai, (1998). Can prostitutes marry? Thai attitudes toward female sex workers. Social Science Medicine, 47(2), 255\u2013267. doi: 10.1016/S0277-9536(98)00089-6", "@id": "46", "ref-info": {"ref-publicationyear": {"@first": "1998"}, "ref-title": {"ref-titletext": "Can prostitutes marry? Thai attitudes toward female sex workers"}, "refd-itemidlist": {"itemid": {"$": "0031833566", "@idtype": "SGR"}}, "ref-volisspag": {"voliss": {"@volume": "47", "@issue": "2"}, "pagerange": {"@first": "255", "@last": "267"}}, "ref-authors": {"author": [{"@seq": "1", "ce:initials": "S.", "@_fa": "true", "ce:surname": "Peracca", "ce:indexed-name": "Peracca S."}, {"@seq": "2", "ce:initials": "J.", "@_fa": "true", "ce:surname": "Knodel", "ce:indexed-name": "Knodel J."}, {"@seq": "3", "ce:initials": "C.", "@_fa": "true", "ce:surname": "Saengtienchai", "ce:indexed-name": "Saengtienchai C."}]}, "ref-sourcetitle": "Social Science Medicine"}}, {"ref-fulltext": "C.Ryan,, & D.Montgomery, (1994). The attitudes of Bakewell residents to tourism and issues in community responsive tourism. Tourism Management, 15(5), 358\u2013369. doi: 10.1016/0261-5177(94)90090-6", "@id": "47", "ref-info": {"ref-publicationyear": {"@first": "1994"}, "ref-title": {"ref-titletext": "The attitudes of Bakewell residents to tourism and issues in community responsive tourism"}, "refd-itemidlist": {"itemid": {"$": "0000946052", "@idtype": "SGR"}}, "ref-volisspag": {"voliss": {"@volume": "15", "@issue": "5"}, "pagerange": {"@first": "358", "@last": "369"}}, "ref-authors": {"author": [{"@seq": "1", "ce:initials": "C.", "@_fa": "true", "ce:surname": "Ryan", "ce:indexed-name": "Ryan C."}, {"@seq": "2", "ce:initials": "D.", "@_fa": "true", "ce:surname": "Montgomery", "ce:indexed-name": "Montgomery D."}]}, "ref-sourcetitle": "Tourism Management"}}, {"ref-fulltext": "R.Sharpley, (1999). Tourism, tourists and society. Huntingdon: ELM.", "@id": "48", "ref-info": {"ref-publicationyear": {"@first": "1999"}, "refd-itemidlist": {"itemid": {"$": "0003877924", "@idtype": "SGR"}}, "ref-text": "Huntingdon: ELM", "ref-authors": {"author": [{"@seq": "1", "ce:initials": "R.", "@_fa": "true", "ce:surname": "Sharpley", "ce:indexed-name": "Sharpley R."}]}, "ref-sourcetitle": "Tourism, tourists and society"}}, {"ref-fulltext": "G.Shaw,, & A.M.William, (2002). Critical issues in tourism (2nd ed.). London: Blackwell.", "@id": "49", "ref-info": {"ref-publicationyear": {"@first": "2002"}, "refd-itemidlist": {"itemid": {"$": "0003681858", "@idtype": "SGR"}}, "ref-text": "2nd ed., London: Blackwell", "ref-authors": {"author": [{"@seq": "1", "ce:initials": "G.", "@_fa": "true", "ce:surname": "Shaw", "ce:indexed-name": "Shaw G."}, {"@seq": "2", "ce:initials": "A.M.", "@_fa": "true", "ce:surname": "William", "ce:indexed-name": "William A.M."}]}, "ref-sourcetitle": "Critical issues in tourism"}}, {"ref-fulltext": "P.Singh,, & S.A.Hart, (2007). Sex workers and cultural policy: Mapping the issues and actors in Thailand. Review of Policy Research, 24(2), 155\u2013173. doi: 10.1111/j.1541-1338.2007.00274.x", "@id": "50", "ref-info": {"ref-publicationyear": {"@first": "2007"}, "ref-title": {"ref-titletext": "Sex workers and cultural policy: Mapping the issues and actors in Thailand"}, "refd-itemidlist": {"itemid": {"$": "33947577714", "@idtype": "SGR"}}, "ref-volisspag": {"voliss": {"@volume": "24", "@issue": "2"}, "pagerange": {"@first": "155", "@last": "173"}}, "ref-authors": {"author": [{"@seq": "1", "ce:initials": "P.", "@_fa": "true", "ce:surname": "Singh", "ce:indexed-name": "Singh P."}, {"@seq": "2", "ce:initials": "S.A.", "@_fa": "true", "ce:surname": "Hart", "ce:indexed-name": "Hart S.A."}]}, "ref-sourcetitle": "Review of Policy Research"}}, {"ref-fulltext": "H.Tajfel, (1981). Human groups and social categories. Cambridge: Cambridge University Press.", "@id": "51", "ref-info": {"ref-publicationyear": {"@first": "1981"}, "refd-itemidlist": {"itemid": {"$": "0003493750", "@idtype": "SGR"}}, "ref-text": "Cambridge: Cambridge University Press", "ref-authors": {"author": [{"@seq": "1", "ce:initials": "H.", "@_fa": "true", "ce:surname": "Tajfel", "ce:indexed-name": "Tajfel H."}]}, "ref-sourcetitle": "Human groups and social categories"}}, {"ref-fulltext": "C.Tosun, (2002). Host perceptions of impacts: A comparative tourism study. Annals of Tourism Research, 29(1), 231\u2013253. doi: 10.1016/S0160-7383(01)00039-1", "@id": "52", "ref-info": {"ref-publicationyear": {"@first": "2002"}, "ref-title": {"ref-titletext": "Host perceptions of impacts: A comparative tourism study"}, "refd-itemidlist": {"itemid": {"$": "0036136511", "@idtype": "SGR"}}, "ref-volisspag": {"voliss": {"@volume": "29", "@issue": "1"}, "pagerange": {"@first": "231", "@last": "253"}}, "ref-authors": {"author": [{"@seq": "1", "ce:initials": "C.", "@_fa": "true", "ce:surname": "Tosun", "ce:indexed-name": "Tosun C."}]}, "ref-sourcetitle": "Annals of Tourism Research"}}, {"ref-fulltext": "S.Tovanabutra,, G.H.Kijak,, C.Beyrer,, C.Gammon-Richardson,, S.Sakkhachornphop,, T.Vongchak,, \u2026 F.E.Mccutchan, (2007). Identification of CRF34_01B, a second circulating recombinant form unrelated to and more complex than CRF15_01B, among injecting drug users in Northern Thailand. AIDS Research and Human Retroviruses, 23(6), 829\u2013833. doi: 10.1089/aid.2006.0300", "@id": "53", "ref-info": {"ref-publicationyear": {"@first": "2007"}, "ref-title": {"ref-titletext": "Identification of CRF34_01B, a second circulating recombinant form unrelated to and more complex than CRF15_01B, among injecting drug users in Northern Thailand"}, "refd-itemidlist": {"itemid": {"$": "34447290210", "@idtype": "SGR"}}, "ref-volisspag": {"voliss": {"@volume": "23", "@issue": "6"}, "pagerange": {"@first": "829", "@last": "833"}}, "ref-authors": {"author": [{"@seq": "1", "ce:initials": "S.", "@_fa": "true", "ce:surname": "Tovanabutra", "ce:indexed-name": "Tovanabutra S."}, {"@seq": "2", "ce:initials": "G.H.", "@_fa": "true", "ce:surname": "Kijak", "ce:indexed-name": "Kijak G.H."}, {"@seq": "3", "ce:initials": "C.", "@_fa": "true", "ce:surname": "Beyrer", "ce:indexed-name": "Beyrer C."}, {"@seq": "4", "ce:initials": "C.", "@_fa": "true", "ce:surname": "Gammon-Richardson", "ce:indexed-name": "Gammon-Richardson C."}, {"@seq": "5", "ce:initials": "S.", "@_fa": "true", "ce:surname": "Sakkhachornphop", "ce:indexed-name": "Sakkhachornphop S."}, {"@seq": "6", "ce:initials": "T.", "@_fa": "true", "ce:surname": "Vongchak", "ce:indexed-name": "Vongchak T."}, {"@seq": "7", "ce:initials": "F.E.", "@_fa": "true", "ce:surname": "Mccutchan", "ce:indexed-name": "Mccutchan F.E."}]}, "ref-sourcetitle": "AIDS Research and Human Retroviruses"}}, {"ref-fulltext": "A.Vargas-Sanchez,, M.A.Plaza-Mejjia,, & N.Porras-Bueno, (2009). Understanding residents\u2019 attitudes toward the development of industrial tourism in a former mining community. Journal of Travel Research, 47(3), 373\u2013387. doi: 10.1177/0047287508322783", "@id": "54", "ref-info": {"ref-publicationyear": {"@first": "2009"}, "ref-title": {"ref-titletext": "Understanding residents\u2019 attitudes toward the development of industrial tourism in a former mining community"}, "refd-itemidlist": {"itemid": {"$": "58149512611", "@idtype": "SGR"}}, "ref-volisspag": {"voliss": {"@volume": "47", "@issue": "3"}, "pagerange": {"@first": "373", "@last": "387"}}, "ref-authors": {"author": [{"@seq": "1", "ce:initials": "A.", "@_fa": "true", "ce:surname": "Vargas-Sanchez", "ce:indexed-name": "Vargas-Sanchez A."}, {"@seq": "2", "ce:initials": "M.A.", "@_fa": "true", "ce:surname": "Plaza-Mejjia", "ce:indexed-name": "Plaza-Mejjia M.A."}, {"@seq": "3", "ce:initials": "N.", "@_fa": "true", "ce:surname": "Porras-Bueno", "ce:indexed-name": "Porras-Bueno N."}]}, "ref-sourcetitle": "Journal of Travel Research"}}, {"ref-fulltext": "C.A.Ward,, S.Bochner,, & A.Furnham, (2001). The psychology of culture shock. Hove: Routledge.", "@id": "55", "ref-info": {"ref-publicationyear": {"@first": "2001"}, "refd-itemidlist": {"itemid": {"$": "0004154390", "@idtype": "SGR"}}, "ref-text": "Hove: Routledge", "ref-authors": {"author": [{"@seq": "1", "ce:initials": "C.A.", "@_fa": "true", "ce:surname": "Ward", "ce:indexed-name": "Ward C.A."}, {"@seq": "2", "ce:initials": "S.", "@_fa": "true", "ce:surname": "Bochner", "ce:indexed-name": "Bochner S."}, {"@seq": "3", "ce:initials": "A.", "@_fa": "true", "ce:surname": "Furnham", "ce:indexed-name": "Furnham A."}]}, "ref-sourcetitle": "The psychology of culture shock"}}, {"ref-fulltext": "P.White, (1974). The social impacts of tourism on host communities: A study of language change in Switzerland (Research Paper 9). Oxford: School of Geography, Oxford University.", "@id": "56", "ref-info": {"ref-publicationyear": {"@first": "1974"}, "refd-itemidlist": {"itemid": {"$": "84943457348", "@idtype": "SGR"}}, "ref-text": "The social impacts of tourism on host communities: A study of language change in Switzerland (Research Paper 9). Oxford: School of Geography, Oxford University", "ref-authors": {"author": [{"@seq": "1", "ce:initials": "P.", "@_fa": "true", "ce:surname": "White", "ce:indexed-name": "White P."}]}}}, {"ref-fulltext": "A.M.Williams,, & C.M.Hall, (2000). Tourism and migration: New relationships between production and consumption. Tourism Geographies, 2(1), 5\u201327. doi: 10.1080/146166800363420", "@id": "57", "ref-info": {"ref-publicationyear": {"@first": "2000"}, "ref-title": {"ref-titletext": "Tourism and migration: New relationships between production and consumption"}, "refd-itemidlist": {"itemid": {"$": "0002711834", "@idtype": "SGR"}}, "ref-volisspag": {"voliss": {"@volume": "2", "@issue": "1"}, "pagerange": {"@first": "5", "@last": "27"}}, "ref-authors": {"author": [{"@seq": "1", "ce:initials": "A.M.", "@_fa": "true", "ce:surname": "Williams", "ce:indexed-name": "Williams A.M."}, {"@seq": "2", "ce:initials": "C.M.", "@_fa": "true", "ce:surname": "Hall", "ce:indexed-name": "Hall C.M."}]}, "ref-sourcetitle": "Tourism Geographies"}}]}}}}, "affiliation": {"affiliation-city": "Bangkok", "@id": "60028190", "affilname": "Chulalongkorn University", "@href": "https://api.elsevier.com/content/affiliation/affiliation_id/60028190", "affiliation-country": "Thailand"}, "coredata": {"srctype": "j", "eid": "2-s2.0-84943448265", "dc:description": "The economic development brought about by tourism often induces migration to an emerging tourism region. A constructivist paradigm with semi-structured interviews was employed. This paper aims to interpret residents' social constructions towards the sociocultural impacts of tourism-induced internal labour migration in a Thai context. Western studies assume there are clear negative and positive impacts of tourism development. These sociocultural impacts of tourism in the Western literature are applicable in a Thai context. However, most previous studies on sociocultural impacts of tourism look from the outside but it is significant that nobody has looked from an inside Thai perspective. Local residents in Koh Samui attribute the majority of sociocultural impacts to labour migration from the Isan region of Thailand. This paper starts with an analysis of labour forces in Thailand, and how tourism and labour migration are interrelated. In addition, the ethnic identity of the Isan people is examined.", "prism:coverDate": "2015-11-02", "prism:aggregationType": "Journal", "prism:url": "https://api.elsevier.com/content/abstract/scopus_id/84943448265", "dc:creator": {"author": [{"ce:given-name": "Somruthai", "preferred-name": {"ce:given-name": "Somruthai", "ce:initials": "S.", "ce:surname": "Soontayatron", "ce:indexed-name": "Soontayatron S."}, "@seq": "1", "ce:initials": "S.", "@_fa": "true", "affiliation": {"@id": "60028190", "@href": "https://api.elsevier.com/content/affiliation/affiliation_id/60028190"}, "ce:surname": "Soontayatron", "@auid": "55875068200", "author-url": "https://api.elsevier.com/content/author/author_id/55875068200", "ce:indexed-name": "Soontayatron S."}]}, "link": [{"@_fa": "true", "@rel": "self", "@href": "https://api.elsevier.com/content/abstract/scopus_id/84943448265"}, {"@_fa": "true", "@rel": "scopus", "@href": "https://www.scopus.com/inward/record.uri?partnerID=HzOxMe3b&scp=84943448265&origin=inward"}, {"@_fa": "true", "@rel": "scopus-citedby", "@href": "https://www.scopus.com/inward/citedby.uri?partnerID=HzOxMe3b&scp=84943448265&origin=inward"}], "source-id": "12117", "citedby-count": "3", "prism:volume": "20", "subtype": "ar", "dc:title": "Residents\u2019 Perceptions Towards Sociocultural Impacts Induced by Internal Migration", "openaccess": "0", "prism:issn": "17416507 10941665", "publishercopyright": "\u00a9 2014 Asia Pacific Tourism Association.", "prism:issueIdentifier": "11", "subtypeDescription": "Article", "prism:publicationName": "Asia Pacific Journal of Tourism Research", "prism:pageRange": "1234-1245", "prism:endingPage": "1245", "openaccessFlag": "false", "prism:doi": "10.1080/10941665.2014.975826", "prism:startingPage": "1234", "dc:identifier": "SCOPUS_ID:84943448265", "dc:publisher": "Routledge"}, "idxterms": null, "language": {"@xml:lang": "eng"}, "authkeywords": {"author-keyword": [{"@_fa": "true", "$": "internal migration"}, {"@_fa": "true", "$": "Isan migrant workers"}, {"@_fa": "true", "$": "residents\u2019 perceptions"}, {"@_fa": "true", "$": "sociocultural impacts"}, {"@_fa": "true", "$": "tourism development"}]}, "subject-areas": {"subject-area": [{"@_fa": "true", "$": "Geography, Planning and Development", "@code": "3305", "@abbrev": "SOCI"}, {"@_fa": "true", "$": "Tourism, Leisure and Hospitality Management", "@code": "1409", "@abbrev": "BUSI"}]}, "authors": {"author": [{"ce:given-name": "Somruthai", "preferred-name": {"ce:given-name": "Somruthai", "ce:initials": "S.", "ce:surname": "Soontayatron", "ce:indexed-name": "Soontayatron S."}, "@seq": "1", "ce:initials": "S.", "@_fa": "true", "affiliation": {"@id": "60028190", "@href": "https://api.elsevier.com/content/affiliation/affiliation_id/60028190"}, "ce:surname": "Soontayatron", "@auid": "55875068200", "author-url": "https://api.elsevier.com/content/author/author_id/55875068200", "ce:indexed-name": "Soontayatron S."}]}}}