{"abstracts-retrieval-response": {"item": {"ait:process-info": {"ait:status": {"@state": "update", "@type": "core", "@stage": "S300"}, "ait:date-delivered": {"@day": "18", "@year": "2019", "@timestamp": "2019-11-18T09:38:00.000000-05:00", "@month": "11"}, "ait:date-sort": {"@day": "01", "@year": "2012", "@month": "12"}}, "bibrecord": {"head": {"author-group": {"affiliation": {"city-group": "Patumwan, Bangkok 10330", "country": "Thailand", "address-part": "254 Phayathai Road", "@afid": "60028190", "@country": "tha", "organization": [{"$": "Department of Electrical Engineering"}, {"$": "Faculty of Engineering"}, {"$": "Chulalongkorn University"}], "affiliation-id": {"@afid": "60028190", "@dptid": "113845132"}, "@dptid": "113845132"}, "author": [{"ce:given-name": "Vatee", "preferred-name": {"ce:given-name": "Vatee", "ce:initials": "V.", "ce:surname": "Laoharojanaphand", "ce:indexed-name": "Laoharojanaphand V."}, "@seq": "1", "ce:initials": "V.", "@_fa": "true", "ce:surname": "Laoharojanaphand", "@auid": "55901315900", "ce:indexed-name": "Laoharojanaphand V."}, {"ce:given-name": "Naebboon", "preferred-name": {"ce:given-name": "Naebboon", "ce:initials": "N.", "ce:surname": "Hoonchareon", "ce:indexed-name": "Hoonchareon N."}, "@seq": "2", "ce:initials": "N.", "@_fa": "true", "ce:surname": "Hoonchareon", "@auid": "24177824600", "ce:indexed-name": "Hoonchareon N."}]}, "citation-title": "Fault recorder data refinement for accurate fault location in a transmission system", "abstracts": "This paper presents a data refinement process for fault data recorded by a group of associated digital fault recorders (DFR) for improving accuracy in line fault location in a transmission system. The refinement process employs weighted least square state estimation technique to compute calibration factors, using the measurements of pre-fault data of voltage and current from multiple correlated DFRs. The factors then are applied to correcting the corresponding during-fault data. To verify the effectiveness of the proposed refinement method, both simulated data from the IEEE 14 bus test system and field measured data from the Thailand's transmission system have been tested using the standard two-terminal fault location algorithm. Test results strongly confirm that the improved accuracy in locating fault on a transmission line can be obtained when compares to the respective unrefined cases. \u00a9 2012 IEEE.", "correspondence": {"affiliation": {"city-group": "Patumwan, Bangkok 10330", "country": "Thailand", "address-part": "254 Phayathai Road", "@country": "tha", "organization": [{"$": "Department of Electrical Engineering"}, {"$": "Faculty of Engineering"}, {"$": "Chulalongkorn University"}]}}, "citation-info": {"author-keywords": {"author-keyword": [{"$": "data refinement", "@xml:lang": "eng"}, {"$": "line fault location", "@xml:lang": "eng"}, {"$": "state estimation", "@xml:lang": "eng"}]}, "citation-type": {"@code": "cp"}, "citation-language": {"@language": "English", "@xml:lang": "eng"}, "abstract-language": {"@language": "English", "@xml:lang": "eng"}}, "source": {"sourcetitle-abbrev": "Proc. - Power Eng. Autom. Conf., PEAM", "@country": "usa", "issuetitle": "Proceedings - Power Engineering and Automation Conference, PEAM 2012", "@type": "p", "publicationyear": {"@first": "2012"}, "isbn": {"$": "9781457716003", "@length": "13"}, "additional-srcinfo": {"conferenceinfo": {"confpublication": {"procpagerange": "var.pagings"}, "confevent": {"confname": "2012 IEEE Power Engineering and Automation Conference, PEAM 2012", "confsponsors": {"confsponsor": [{"$": "IEEE Wuhan Section"}, {"$": "Shanghai Jiao Tong University"}, {"$": "Wuhan University"}, {"$": "Wuhan University of Technology"}, {"$": "Jiangsu University"}], "@complete": "n"}, "confcatnumber": "CFP1273M-ART", "conflocation": {"city-group": "Wuhan", "@country": "chn"}, "confcode": "100324", "confdate": {"enddate": {"@day": "16", "@year": "2012", "@month": "09"}, "startdate": {"@day": "14", "@year": "2012", "@month": "09"}}}}}, "sourcetitle": "Proceedings - Power Engineering and Automation Conference, PEAM 2012", "article-number": "6612517", "@srcid": "21100264285", "publicationdate": {"year": "2012", "date-text": {"@xfab-added": "true", "$": "2012"}}}, "enhancement": {"classificationgroup": {"classifications": [{"@type": "ASJC", "classification": [{"$": "2102"}, {"$": "2103"}]}, {"@type": "CPXCLASS", "classification": [{"classification-code": "602.2", "classification-description": "Mechanical Transmissions"}, {"classification-code": "706.1.1", "classification-description": "Electric Power Transmission"}, {"classification-code": "731.1", "classification-description": "Control Systems"}]}, {"@type": "GEOCLASS", "classification": {"classification-code": "Related Topics"}}, {"@type": "SUBJABBR", "classification": "ENER"}]}}}, "item-info": {"copyright": {"$": "Copyright 2013 Elsevier B.V., All rights reserved.", "@type": "Elsevier"}, "dbcollection": [{"$": "CPX"}, {"$": "SCOPUS"}, {"$": "Scopusbase"}], "history": {"date-created": {"@day": "30", "@year": "2013", "@month": "10"}}, "itemidlist": {"itemid": [{"$": "370111612", "@idtype": "PUI"}, {"$": "20134416923882", "@idtype": "CPX"}, {"$": "84886423524", "@idtype": "SCP"}, {"$": "84886423524", "@idtype": "SGR"}], "ce:doi": "10.1109/PEAM.2012.6612517"}}, "tail": {"bibliography": {"@refcount": "6", "reference": [{"ref-fulltext": "Meliopoulos, A. P. S., Cokkinides, G. J., Hedrington, C. and Conrad T. L., \"The SuperCalibrator-A Fully Distributed State Estimator\", IEEE Power and Energy Society General Meeting, 2010: 1-8", "@id": "1", "ref-info": {"ref-publicationyear": {"@first": "2010"}, "ref-title": {"ref-titletext": "The supercalibrator-A fully distributed state estimator"}, "refd-itemidlist": {"itemid": {"$": "78649616742", "@idtype": "SGR"}}, "ref-volisspag": {"pagerange": {"@first": "1", "@last": "8"}}, "ref-authors": {"author": [{"@seq": "1", "ce:initials": "A.P.S.", "@_fa": "true", "ce:surname": "Meliopoulos", "ce:indexed-name": "Meliopoulos A.P.S."}, {"@seq": "2", "ce:initials": "G.J.", "@_fa": "true", "ce:surname": "Cokkinides", "ce:indexed-name": "Cokkinides G.J."}, {"@seq": "3", "ce:initials": "C.", "@_fa": "true", "ce:surname": "Hedrington", "ce:indexed-name": "Hedrington C."}, {"@seq": "4", "ce:initials": "T.L.", "@_fa": "true", "ce:surname": "Conrad", "ce:indexed-name": "Conrad T.L."}]}, "ref-sourcetitle": "IEEE Power and Energy Society General Meeting"}}, {"ref-fulltext": "Meliopoulos, A. P. S., Cokkinides, G. J., Galvan, F., Fardanesh, B. and Mydra P., \"Advances in the SuperCalibrator concept-Practical Implementations\", Hawaii International Conference on System Sciences, 2007", "@id": "2", "ref-info": {"ref-publicationyear": {"@first": "2007"}, "ref-title": {"ref-titletext": "Advances in the SuperCalibrator concept-Practical Implementations"}, "refd-itemidlist": {"itemid": {"$": "39749109329", "@idtype": "SGR"}}, "ref-authors": {"author": [{"@seq": "1", "ce:initials": "A.P.S.", "@_fa": "true", "ce:surname": "Meliopoulos", "ce:indexed-name": "Meliopoulos A.P.S."}, {"@seq": "2", "ce:initials": "G.J.", "@_fa": "true", "ce:surname": "Cokkinides", "ce:indexed-name": "Cokkinides G.J."}, {"@seq": "3", "ce:initials": "F.", "@_fa": "true", "ce:surname": "Galvan", "ce:indexed-name": "Galvan F."}, {"@seq": "4", "ce:initials": "B.", "@_fa": "true", "ce:surname": "Fardanesh", "ce:indexed-name": "Fardanesh B."}, {"@seq": "5", "ce:initials": "P.", "@_fa": "true", "ce:surname": "Mydra", "ce:indexed-name": "Mydra P."}]}, "ref-sourcetitle": "Hawaii International Conference on System Sciences"}}, {"ref-fulltext": "Ebrahimian, R. and Baldick, R., \"State Estimation Distributed Processing\", IEEE Transactions on Power Systems, vol. 15, no. 4, pp. 1240-1246, Nov. 2000.", "@id": "3", "ref-info": {"ref-publicationyear": {"@first": "2000"}, "ref-title": {"ref-titletext": "State estimation distributed processing"}, "refd-itemidlist": {"itemid": {"$": "0034430755", "@idtype": "SGR"}}, "ref-volisspag": {"voliss": {"@volume": "15", "@issue": "4"}, "pagerange": {"@first": "1240", "@last": "1246"}}, "ref-text": "Nov.", "ref-authors": {"author": [{"@seq": "1", "ce:initials": "R.", "@_fa": "true", "ce:surname": "Ebrahimian", "ce:indexed-name": "Ebrahimian R."}, {"@seq": "2", "ce:initials": "R.", "@_fa": "true", "ce:surname": "Baldick", "ce:indexed-name": "Baldick R."}]}, "ref-sourcetitle": "IEEE Transactions on Power Systems"}}, {"ref-fulltext": "Zhong, S. and Abur, A., \"Combined state estimation and measurement calibration\", IEEE Transactions on Power Systems, vol. 20, no. 1, pp. 458-465, Feb. 2005.", "@id": "4", "ref-info": {"ref-publicationyear": {"@first": "2005"}, "ref-title": {"ref-titletext": "Combined state estimation and measurement calibration"}, "refd-itemidlist": {"itemid": {"$": "13844311442", "@idtype": "SGR"}}, "ref-volisspag": {"voliss": {"@volume": "20", "@issue": "1"}, "pagerange": {"@first": "458", "@last": "465"}}, "ref-text": "Feb.", "ref-authors": {"author": [{"@seq": "1", "ce:initials": "S.", "@_fa": "true", "ce:surname": "Zhong", "ce:indexed-name": "Zhong S."}, {"@seq": "2", "ce:initials": "A.", "@_fa": "true", "ce:surname": "Abur", "ce:indexed-name": "Abur A."}]}, "ref-sourcetitle": "IEEE Transactions on Power Systems"}}, {"ref-fulltext": "Abur, A. and Exposito, A. G., Power System State Estimation: Theory and Implementation, 2004", "@id": "5", "ref-info": {"ref-publicationyear": {"@first": "2004"}, "refd-itemidlist": {"itemid": {"$": "14544302923", "@idtype": "SGR"}}, "ref-authors": {"author": [{"@seq": "1", "ce:initials": "A.", "@_fa": "true", "ce:surname": "Abur", "ce:indexed-name": "Abur A."}, {"@seq": "2", "ce:initials": "A.G.", "@_fa": "true", "ce:surname": "Exposito", "ce:indexed-name": "Exposito A.G."}]}, "ref-sourcetitle": "Power System State Estimation: Theory and Implementation"}}, {"ref-fulltext": "IEEE Standard C37. 114\u2122-2004(R2009), \"IEEE Guide for Determining Fault Location on AC Transmission and Distribution Lines\", Jun. 2005", "@id": "6", "ref-info": {"ref-publicationyear": {"@first": "2005"}, "refd-itemidlist": {"itemid": {"$": "0013298255", "@idtype": "SGR"}}, "ref-text": "IEEE Standard C37. 114\u2122-2004(R2009), Jun.", "ref-sourcetitle": "IEEE Guide for Determining Fault Location on AC Transmission and Distribution Lines"}}]}}}}, "affiliation": {"affiliation-city": "Bangkok", "@id": "60028190", "affilname": "Chulalongkorn University", "@href": "https://api.elsevier.com/content/affiliation/affiliation_id/60028190", "affiliation-country": "Thailand"}, "coredata": {"srctype": "p", "eid": "2-s2.0-84886423524", "dc:description": "This paper presents a data refinement process for fault data recorded by a group of associated digital fault recorders (DFR) for improving accuracy in line fault location in a transmission system. The refinement process employs weighted least square state estimation technique to compute calibration factors, using the measurements of pre-fault data of voltage and current from multiple correlated DFRs. The factors then are applied to correcting the corresponding during-fault data. To verify the effectiveness of the proposed refinement method, both simulated data from the IEEE 14 bus test system and field measured data from the Thailand's transmission system have been tested using the standard two-terminal fault location algorithm. Test results strongly confirm that the improved accuracy in locating fault on a transmission line can be obtained when compares to the respective unrefined cases. \u00a9 2012 IEEE.", "prism:coverDate": "2012-12-01", "prism:aggregationType": "Conference Proceeding", "prism:url": "https://api.elsevier.com/content/abstract/scopus_id/84886423524", "subtypeDescription": "Conference Paper", "dc:creator": {"author": [{"ce:given-name": "Vatee", "preferred-name": {"ce:given-name": "Vatee", "ce:initials": "V.", "ce:surname": "Laoharojanaphand", "ce:indexed-name": "Laoharojanaphand V."}, "@seq": "1", "ce:initials": "V.", "@_fa": "true", "affiliation": {"@id": "60028190", "@href": "https://api.elsevier.com/content/affiliation/affiliation_id/60028190"}, "ce:surname": "Laoharojanaphand", "@auid": "55901315900", "author-url": "https://api.elsevier.com/content/author/author_id/55901315900", "ce:indexed-name": "Laoharojanaphand V."}]}, "link": [{"@_fa": "true", "@rel": "self", "@href": "https://api.elsevier.com/content/abstract/scopus_id/84886423524"}, {"@_fa": "true", "@rel": "scopus", "@href": "https://www.scopus.com/inward/record.uri?partnerID=HzOxMe3b&scp=84886423524&origin=inward"}, {"@_fa": "true", "@rel": "scopus-citedby", "@href": "https://www.scopus.com/inward/citedby.uri?partnerID=HzOxMe3b&scp=84886423524&origin=inward"}], "prism:isbn": "9781457716003", "prism:publicationName": "Proceedings - Power Engineering and Automation Conference, PEAM 2012", "source-id": "21100264285", "citedby-count": "2", "subtype": "cp", "dc:title": "Fault recorder data refinement for accurate fault location in a transmission system", "openaccess": "0", "openaccessFlag": "false", "prism:doi": "10.1109/PEAM.2012.6612517", "article-number": "6612517", "dc:identifier": "SCOPUS_ID:84886423524"}, "idxterms": {"mainterm": [{"$": "Calibration factors", "@weight": "a", "@candidate": "n"}, {"$": "Data refinements", "@weight": "a", "@candidate": "n"}, {"$": "Digital fault recorder", "@weight": "a", "@candidate": "n"}, {"$": "Field-measured data", "@weight": "a", "@candidate": "n"}, {"$": "Refinement methods", "@weight": "a", "@candidate": "n"}, {"$": "Transmission systems", "@weight": "a", "@candidate": "n"}, {"$": "Two-terminal fault locations", "@weight": "a", "@candidate": "n"}, {"$": "Weighted least square state estimation", "@weight": "a", "@candidate": "n"}]}, "language": {"@xml:lang": "eng"}, "authkeywords": {"author-keyword": [{"@_fa": "true", "$": "data refinement"}, {"@_fa": "true", "$": "line fault location"}, {"@_fa": "true", "$": "state estimation"}]}, "subject-areas": {"subject-area": [{"@_fa": "true", "$": "Energy Engineering and Power Technology", "@code": "2102", "@abbrev": "ENER"}, {"@_fa": "true", "$": "Fuel Technology", "@code": "2103", "@abbrev": "ENER"}]}, "authors": {"author": [{"ce:given-name": "Vatee", "preferred-name": {"ce:given-name": "Vatee", "ce:initials": "V.", "ce:surname": "Laoharojanaphand", "ce:indexed-name": "Laoharojanaphand V."}, "@seq": "1", "ce:initials": "V.", "@_fa": "true", "affiliation": {"@id": "60028190", "@href": "https://api.elsevier.com/content/affiliation/affiliation_id/60028190"}, "ce:surname": "Laoharojanaphand", "@auid": "55901315900", "author-url": "https://api.elsevier.com/content/author/author_id/55901315900", "ce:indexed-name": "Laoharojanaphand V."}, {"ce:given-name": "Naebboon", "preferred-name": {"ce:given-name": "Naebboon", "ce:initials": "N.", "ce:surname": "Hoonchareon", "ce:indexed-name": "Hoonchareon N."}, "@seq": "2", "ce:initials": "N.", "@_fa": "true", "affiliation": {"@id": "60028190", "@href": "https://api.elsevier.com/content/affiliation/affiliation_id/60028190"}, "ce:surname": "Hoonchareon", "@auid": "24177824600", "author-url": "https://api.elsevier.com/content/author/author_id/24177824600", "ce:indexed-name": "Hoonchareon N."}]}}}